povertyInequalityMeasures/__init__.py
povertyInequalityMeasures/inequality.py
povertyInequalityMeasures/poverty.py
povertyinequalitymeasures-1.1.1.dist-info/METADATA
povertyinequalitymeasures-1.1.1.dist-info/WHEEL
povertyinequalitymeasures-1.1.1.dist-info/licenses/LICENSE
povertyinequalitymeasures-1.1.1.dist-info/RECORD
