Metadata-Version: 2.4
Name: povertyInequalityMeasures
Version: 1.1.1
Summary: Calculate some poverty and inequality measures. Based on the Wold Bank Poverty and Inequality Handbook: https://documents1.worldbank.org/curated/en/488081468157174849/pdf/483380PUB0Pove101OFFICIAL0USE0ONLY1.pdf
Project-URL: Homepage, https://github.com/danmermel/povertyInequalityMeasures
Project-URL: Issues, https://github.com/danmermel/povertyInequalityMeasures/issues
Author-email: Daniel Mermelstein <danmermel@gmail.com>
License-Expression: MIT
License-File: LICENSE
Classifier: Operating System :: OS Independent
Classifier: Programming Language :: Python :: 3
Requires-Python: >=3.8
